bikeshop/__init__.py
bikeshop/__manifest__.py
bikeshop/data/bikeshop_delay_reason_data.xml
bikeshop/data/mail_activity_type_data.xml
bikeshop/data/sale_demo.xml
bikeshop/i18n/bikeshop.pot
bikeshop/i18n/de.po
bikeshop/i18n/en_US.po
bikeshop/i18n/legalcode.txt
bikeshop/i18n/nl.po
bikeshop/i18n/sv.po
bikeshop/models/__init__.py
bikeshop/models/bikeshop_bicycle.py
bikeshop/models/bikeshop_delay_reason.py
bikeshop/models/mail_activity.py
bikeshop/models/mail_followers.py
bikeshop/models/product_product.py
bikeshop/models/res_partner.py
bikeshop/models/sale_order.py
bikeshop/security/ir.model.access.csv
bikeshop/security/res_groups.xml
bikeshop/static/description/bicycles.png
bikeshop/static/description/bikeshed.png
bikeshop/static/description/icon.png
bikeshop/static/description/icon.svg
bikeshop/static/description/index.html
bikeshop/static/description/logo.png
bikeshop/static/description/logo.svg
bikeshop/static/description/queue.png
bikeshop/static/description/wo_screenshot.png
bikeshop/static/description/work_order.png
bikeshop/views/bikeshop_bicycle_views.xml
bikeshop/views/bikeshop_delay_reason_views.xml
bikeshop/views/bikeshop_menus.xml
bikeshop/views/product_product_views.xml
bikeshop/views/res_partner_views.xml
bikeshop/views/sale_order_views.xml
odoo_bikeshop-0.0.2.dist-info/LICENSE
odoo_bikeshop-0.0.2.dist-info/METADATA
odoo_bikeshop-0.0.2.dist-info/WHEEL
odoo_bikeshop-0.0.2.dist-info/RECORD
