Metadata-Version: 2.1
Name: odoo-bikeshop
Version: 0.0.2
Summary: A work order management solution for bicycle repair shops built as an Odoo 17 addon.
Home-page: https://www.atlbikeshed.com
License: GPL-3.0-or-later
Keywords: odoo,odoo18,bicycle,bike shop
Author: Sam Whited
Author-email: sam@samwhited.com
Requires-Python: >=3.8,<4.0
Classifier: Development Status :: 4 - Beta
Classifier: Environment :: Plugins
Classifier: Framework :: Odoo :: 18.0
Classifier: Intended Audience :: Other Audience
Classifier: License :: OSI Approved :: GNU General Public License v3 or later (GPLv3+)
Classifier: Natural Language :: English
Classifier: Operating System :: OS Independent
Classifier: Programming Language :: Python :: 3
Classifier: Programming Language :: Python :: 3.8
Classifier: Programming Language :: Python :: 3.9
Classifier: Programming Language :: Python :: 3.10
Classifier: Programming Language :: Python :: 3.11
Classifier: Programming Language :: Python :: 3.12
Classifier: Topic :: Office/Business
Project-URL: Bug Tracker, https://codeberg.org/atlbikeshed/odoo-bikeshop/issues
Project-URL: Repository, https://codeberg.org/atlbikeshed/odoo-bikeshop/
